pimpmyrice_server/__init__.py
pimpmyrice_server/__main__.py
pimpmyrice_server/api.py
pimpmyrice_server/cli.py
pimpmyrice_server/files.py
pimpmyrice_server/tray.py
pimpmyrice_server/assets/__init__.py
pimpmyrice_server/assets/pimp.ico
pimpmyrice_server-0.1.0.dist-info/LICENSE
pimpmyrice_server-0.1.0.dist-info/METADATA
pimpmyrice_server-0.1.0.dist-info/WHEEL
pimpmyrice_server-0.1.0.dist-info/entry_points.txt
pimpmyrice_server-0.1.0.dist-info/top_level.txt
pimpmyrice_server-0.1.0.dist-info/RECORD
